[
    {
        "id": "2ac0f725-7c6f-4d54-a6c5-c79f61b5c3ed",
        "title": "Skin politics four new",
        "slug": "relationship",
        "description": "Sometimes example care company American walk national. Window shoulder music term throughout thing. Ten upon difficult firm.",
        "sku": "0184031421734",
        "price": 77.66,
        "discount_price": null,
        "currency": "USD",
        "stock": 39,
        "is_active": true,
        "rating": 1.4,
        "review_count": 255,
        "seller_id": "489eb275-d47b-415b-829d-e9a2ed20f386",
        "category_id": "1",
        "brand_id": "1"
    },
    {
        "id": "055b8203-90a0-4aa7-9d40-49daec666adf",
        "title": "She role low former",
        "slug": "little-tell-outside",
        "description": "Wall deal want call. Despite air week either.\nLetter mouth institution hospital. Under TV rock raise sell.\nMajority effort play girl. Girl require ok wonder. Author change address series admit.",
        "sku": "2862151519859",
        "price": 209.23,
        "discount_price": 305.19,
        "currency": "USD",
        "stock": 359,
        "is_active": true,
        "rating": 3.1,
        "review_count": 360,
        "seller_id": "9503929f-e7c5-4ba4-9aec-61c1a6ad602f",
        "category_id": "1",
        "brand_id": "1"
    },
    {
        "id": "aa17f2dc-548b-4f9f-836d-96e09e313afd",
        "title": "Young people owner environment",
        "slug": "trip-issue-again",
        "description": "Exist piece trial yeah citizen them economy never. Seat once why second individual spring fire scene. Identify most wish every.",
        "sku": "3031789877061",
        "price": 194.37,
        "discount_price": 63.09,
        "currency": "USD",
        "stock": 39,
        "is_active": true,
        "rating": 4.1,
        "review_count": 564,
        "seller_id": "489eb275-d47b-415b-829d-e9a2ed20f386",
        "category_id": "1",
        "brand_id": "1"
    },
    {
        "id": "498bd03f-2054-40b0-ab0e-60f1c9bf0e07",
        "title": "Administration course until",
        "slug": "quite-take-level",
        "description": "Go boy will central now. Choose not allow standard. Project concern ok perform life around her. Argue why black population.",
        "sku": "1872872699113",
        "price": 362.08,
        "discount_price": 298.79,
        "currency": "USD",
        "stock": 70,
        "is_active": true,
        "rating": 4.0,
        "review_count": 404,
        "seller_id": "9503929f-e7c5-4ba4-9aec-61c1a6ad602f",
        "category_id": "1",
        "brand_id": "1"
    },
    {
        "id": "a9059eb6-ceda-48ce-9f75-d38f6260cbc1",
        "title": "Boy now few citizen",
        "slug": "few-than-tax-them",
        "description": "Same they way especially knowledge industry. Add guess wish around sea staff. Up happen cut wear mouth seat guy.",
        "sku": "2268453518871",
        "price": 143.49,
        "discount_price": null,
        "currency": "USD",
        "stock": 340,
        "is_active": true,
        "rating": 1.2,
        "review_count": 476,
        "seller_id": "472acad9-7832-42a5-bd60-b83612a6e038",
        "category_id": "1",
        "brand_id": "1"
    },
    {
        "id": "3100e37a-35df-451f-b46e-a2fa0e1d0d53",
        "title": "Professor sometimes find",
        "slug": "political-mother",
        "description": "As address similar. Phone mind citizen popular build together. Blue edge leave move.",
        "sku": "4633390117902",
        "price": 127.49,
        "discount_price": null,
        "currency": "USD",
        "stock": 109,
        "is_active": true,
        "rating": 3.9,
        "review_count": 501,
        "seller_id": "472acad9-7832-42a5-bd60-b83612a6e038",
        "category_id": "1",
        "brand_id": "1"
    },
    {
        "id": "a551fa3e-5f2d-4f12-aca4-b95fed1e3c0a",
        "title": "Could picture",
        "slug": "follow-positive",
        "description": "Attention market describe father for ahead into. Success manager country bring send.\nKeep teacher image community science two central. Build stuff but none plant.",
        "sku": "0560098515669",
        "price": 97.87,
        "discount_price": 64.18,
        "currency": "USD",
        "stock": 34,
        "is_active": true,
        "rating": 2.9,
        "review_count": 633,
        "seller_id": "da69d0ee-a499-4899-83dc-1831bf8eacbd",
        "category_id": "1",
        "brand_id": "1"
    },
    {
        "id": "3b839fbe-6cf6-468c-903d-2cdcfc306107",
        "title": "Than chance",
        "slug": "customer-hand",
        "description": "Level huge pick avoid. Business knowledge crime Republican thank. Language instead statement serve. Front some particular Mrs run.",
        "sku": "6559981368646",
        "price": 219.01,
        "discount_price": null,
        "currency": "USD",
        "stock": 129,
        "is_active": true,
        "rating": 4.5,
        "review_count": 250,
        "seller_id": "472acad9-7832-42a5-bd60-b83612a6e038",
        "category_id": "1",
        "brand_id": "1"
    },
    {
        "id": "9b600b6b-5457-4de4-a761-6a50d3e4c7cb",
        "title": "Resource Republican item general",
        "slug": "eight-challenge",
        "description": "Right the student pull. Business walk north world consumer full whole strategy. Minute television else case heart exist I. Use wide specific call they great small.",
        "sku": "6644316450230",
        "price": 459.96,
        "discount_price": 225.12,
        "currency": "USD",
        "stock": 412,
        "is_active": true,
        "rating": 2.8,
        "review_count": 607,
        "seller_id": "ad3ed306-dc0e-454a-9ec3-edcc3d5e56ea",
        "category_id": "1",
        "brand_id": "1"
    },
    {
        "id": "6ea911e9-86a5-4681-b7cf-0b59ca10a341",
        "title": "Professor exactly catch",
        "slug": "opportunity-law",
        "description": "Prove relate officer hard.\nHalf state then bill site. Oil some writer become door president. Accept oil growth condition television half.",
        "sku": "8664966251672",
        "price": 248.76,
        "discount_price": null,
        "currency": "USD",
        "stock": 197,
        "is_active": true,
        "rating": 3.8,
        "review_count": 874,
        "seller_id": "9503929f-e7c5-4ba4-9aec-61c1a6ad602f",
        "category_id": "1",
        "brand_id": "1"
    },
    {
        "id": "ce79e8c5-6018-499d-85a2-3779ae2ca256",
        "title": "Brother father",
        "slug": "possible-give",
        "description": "Deep husband local decide. Make work guess quality. Call involve speak best one prevent.\nAuthor detail sister against share ground sister fly. Administration project now them state situation blue.",
        "sku": "0900625426851",
        "price": 459.59,
        "discount_price": 110.88,
        "currency": "USD",
        "stock": 271,
        "is_active": true,
        "rating": 1.9,
        "review_count": 276,
        "seller_id": "489eb275-d47b-415b-829d-e9a2ed20f386",
        "category_id": "1",
        "brand_id": "1"
    },
    {
        "id": "322e4e79-ece9-402b-b12c-286b77d34f2f",
        "title": "Occur",
        "slug": "then-should-treat",
        "description": "Them across despite life. Cultural whether watch law.\nThus short network health authority bad. Education space begin arm paper relate yet.",
        "sku": "1919619068754",
        "price": 319.52,
        "discount_price": 86.98,
        "currency": "USD",
        "stock": 477,
        "is_active": true,
        "rating": 1.7,
        "review_count": 703,
        "seller_id": "472acad9-7832-42a5-bd60-b83612a6e038",
        "category_id": "1",
        "brand_id": "1"
    },
    {
        "id": "b8a37a70-03cf-4d3a-81b1-0efc35f4aba9",
        "title": "Blue eye",
        "slug": "cell-visit-explain",
        "description": "Manager successful determine during lose particularly authority. Group beautiful who building memory important. Model money push.",
        "sku": "9286092131629",
        "price": 447.69,
        "discount_price": 49.1,
        "currency": "USD",
        "stock": 31,
        "is_active": true,
        "rating": 3.6,
        "review_count": 959,
        "seller_id": "9503929f-e7c5-4ba4-9aec-61c1a6ad602f",
        "category_id": "1",
        "brand_id": "1"
    },
    {
        "id": "68723a55-d358-4fc1-bb21-f6ca4d6aeab1",
        "title": "Safe",
        "slug": "wide-base-or",
        "description": "Pull wind particular scene risk bed. Turn father course conference personal. Not thus movie trip. Himself party general despite.",
        "sku": "3997028345459",
        "price": 340.02,
        "discount_price": 56.5,
        "currency": "USD",
        "stock": 499,
        "is_active": true,
        "rating": 3.8,
        "review_count": 435,
        "seller_id": "472acad9-7832-42a5-bd60-b83612a6e038",
        "category_id": "1",
        "brand_id": "1"
    },
    {
        "id": "1d649d3d-cc25-48b1-b5ca-7c3d482c696d",
        "title": "Class similar",
        "slug": "parent-evidence-dog",
        "description": "During every president question during something increase.\nGrowth day reveal speech something onto suffer. Vote reflect including agency.\nBlue save laugh herself.",
        "sku": "7928775822432",
        "price": 431.86,
        "discount_price": 300.27,
        "currency": "USD",
        "stock": 404,
        "is_active": true,
        "rating": 4.0,
        "review_count": 982,
        "seller_id": "472acad9-7832-42a5-bd60-b83612a6e038",
        "category_id": "1",
        "brand_id": "1"
    },
    {
        "id": "e645f097-5fed-4f56-8190-d0d77389f6b9",
        "title": "Agree without west",
        "slug": "young-action-plant",
        "description": "Lose change and in but a believe. Deal market sit market contain. Policy development born really worker first power.\nAnything tax product eat during single. Focus artist offer admit would.",
        "sku": "2489573893963",
        "price": 409.21,
        "discount_price": 6.42,
        "currency": "USD",
        "stock": 144,
        "is_active": true,
        "rating": 2.0,
        "review_count": 802,
        "seller_id": "9503929f-e7c5-4ba4-9aec-61c1a6ad602f",
        "category_id": "1",
        "brand_id": "1"
    },
    {
        "id": "ae242a55-eada-4ad0-b221-8384cf3fdab2",
        "title": "Country information",
        "slug": "leave-friend-off",
        "description": "Recent say shoulder southern would pattern heavy.\nEight him ten while. Couple role three dinner final note. Reach find plan they lot level describe environment.\nDevelopment executive plan.",
        "sku": "7811234001113",
        "price": 81.44,
        "discount_price": 243.7,
        "currency": "USD",
        "stock": 55,
        "is_active": true,
        "rating": 2.4,
        "review_count": 833,
        "seller_id": "472acad9-7832-42a5-bd60-b83612a6e038",
        "category_id": "1",
        "brand_id": "1"
    },
    {
        "id": "c49bd54a-1817-461b-a3f0-f0d8c8fbba6f",
        "title": "Detail item",
        "slug": "people-stuff",
        "description": "Her significant say station stuff anyone medical. Sing she late heavy argue.\nShort address challenge set pressure organization throughout. Nation memory field send. To whatever ago may build.",
        "sku": "8120389954328",
        "price": 321.19,
        "discount_price": 285.34,
        "currency": "USD",
        "stock": 70,
        "is_active": true,
        "rating": 2.5,
        "review_count": 41,
        "seller_id": "9503929f-e7c5-4ba4-9aec-61c1a6ad602f",
        "category_id": "1",
        "brand_id": "1"
    },
    {
        "id": "d3374bc5-b56d-450a-9df7-2115575c33a1",
        "title": "Chair consumer thought friend",
        "slug": "two-road-kitchen",
        "description": "Remain board cup anything agree maybe. Attention how plan above local.\nExpert trip bring bill anything car not miss. Establish hold discover face.",
        "sku": "0131132685107",
        "price": 17.59,
        "discount_price": null,
        "currency": "USD",
        "stock": 11,
        "is_active": true,
        "rating": 2.1,
        "review_count": 310,
        "seller_id": "ad3ed306-dc0e-454a-9ec3-edcc3d5e56ea",
        "category_id": "1",
        "brand_id": "1"
    },
    {
        "id": "79b7ca94-5e44-41a6-82c9-8222839e8238",
        "title": "Most today art professional",
        "slug": "husband-already",
        "description": "Young white trial still down crime wish rather. Foreign rock scene carry simple.\nEverything organization bar group. Finish other trouble particular.",
        "sku": "9296601005976",
        "price": 123.08,
        "discount_price": 207.47,
        "currency": "USD",
        "stock": 101,
        "is_active": true,
        "rating": 4.0,
        "review_count": 395,
        "seller_id": "9503929f-e7c5-4ba4-9aec-61c1a6ad602f",
        "category_id": "1",
        "brand_id": "1"
    },
    {
        "id": "9d7e720a-076f-408e-a388-2b4ff0a10f19",
        "title": "Prevent employee",
        "slug": "voice-response",
        "description": "In operation again attention sure develop next.\nFar phone minute Mr. My force Mrs likely section community.",
        "sku": "2813029229394",
        "price": 288.94,
        "discount_price": null,
        "currency": "USD",
        "stock": 159,
        "is_active": true,
        "rating": 4.9,
        "review_count": 63,
        "seller_id": "ad3ed306-dc0e-454a-9ec3-edcc3d5e56ea",
        "category_id": "1",
        "brand_id": "1"
    },
    {
        "id": "579c6f3a-1b49-4d9c-aa26-dd68dd90daa2",
        "title": "Wall big trip",
        "slug": "seat-then-because",
        "description": "Financial cover partner now race heavy dream.\nTell everyone change financial fire quite begin.\nPurpose thank walk piece PM describe beyond enjoy. In something move someone animal.",
        "sku": "9845537740361",
        "price": 191.31,
        "discount_price": null,
        "currency": "USD",
        "stock": 157,
        "is_active": true,
        "rating": 2.8,
        "review_count": 84,
        "seller_id": "ad3ed306-dc0e-454a-9ec3-edcc3d5e56ea",
        "category_id": "1",
        "brand_id": "1"
    },
    {
        "id": "b1baab7b-4880-4270-bc91-d9233a29243e",
        "title": "They street and",
        "slug": "win-cell-thought",
        "description": "Over area those now room.\nAbout hour ago whether result. Seek newspaper dog woman also. Or fire campaign rather own imagine word man. Do news focus character these population color.",
        "sku": "1956831224896",
        "price": 55.17,
        "discount_price": 10.17,
        "currency": "USD",
        "stock": 85,
        "is_active": true,
        "rating": 1.5,
        "review_count": 318,
        "seller_id": "9503929f-e7c5-4ba4-9aec-61c1a6ad602f",
        "category_id": "1",
        "brand_id": "1"
    },
    {
        "id": "501ef8d1-1244-4ab6-9797-851b18317bf4",
        "title": "Candidate check know",
        "slug": "school-pretty-ok",
        "description": "Available follow never central. Order figure health trade style participant.\nMaterial movie thousand major conference. Even specific listen.",
        "sku": "6596207493690",
        "price": 82.46,
        "discount_price": null,
        "currency": "USD",
        "stock": 403,
        "is_active": true,
        "rating": 4.6,
        "review_count": 593,
        "seller_id": "489eb275-d47b-415b-829d-e9a2ed20f386",
        "category_id": "1",
        "brand_id": "1"
    },
    {
        "id": "a589d9b3-f0ec-4653-bd00-3e28a118d698",
        "title": "Such little recognize",
        "slug": "condition-pick",
        "description": "Know large crime very field manage. War should popular measure right three.\nGun Mrs stay something one white.",
        "sku": "1595131513011",
        "price": 263.88,
        "discount_price": 96.39,
        "currency": "USD",
        "stock": 381,
        "is_active": true,
        "rating": 3.0,
        "review_count": 371,
        "seller_id": "472acad9-7832-42a5-bd60-b83612a6e038",
        "category_id": "1",
        "brand_id": "1"
    },
    {
        "id": "df4b3b9c-f08c-4edd-afee-e18e5ebd4b10",
        "title": "Too practice role",
        "slug": "song-soldier-than",
        "description": "Individual among he run marriage. Both but section likely even approach. Outside rich individual walk of. Whole need have keep people national in.",
        "sku": "6666854264674",
        "price": 120.04,
        "discount_price": null,
        "currency": "USD",
        "stock": 151,
        "is_active": true,
        "rating": 3.7,
        "review_count": 881,
        "seller_id": "da69d0ee-a499-4899-83dc-1831bf8eacbd",
        "category_id": "1",
        "brand_id": "1"
    },
    {
        "id": "128a3e45-3d50-4cef-a308-eea85f4b8915",
        "title": "Writer recent",
        "slug": "win-would-money",
        "description": "Financial task anything sound. Manage game sing store. Forward pull forget recent concern recognize avoid.",
        "sku": "9641489659306",
        "price": 440.16,
        "discount_price": null,
        "currency": "USD",
        "stock": 315,
        "is_active": true,
        "rating": 4.9,
        "review_count": 482,
        "seller_id": "ad3ed306-dc0e-454a-9ec3-edcc3d5e56ea",
        "category_id": "1",
        "brand_id": "1"
    },
    {
        "id": "b64ec560-c400-4af6-86f3-9098fb5c5ed4",
        "title": "Green chair answer",
        "slug": "require-campaign",
        "description": "Audience example particular accept rise. Stage nice college top learn.\nProve approach center be throughout fund. Support fill under treatment.",
        "sku": "8768467165114",
        "price": 367.95,
        "discount_price": null,
        "currency": "USD",
        "stock": 377,
        "is_active": true,
        "rating": 3.7,
        "review_count": 449,
        "seller_id": "da69d0ee-a499-4899-83dc-1831bf8eacbd",
        "category_id": "1",
        "brand_id": "1"
    },
    {
        "id": "9f1b4eba-3c0e-4ba4-8949-3461c4594349",
        "title": "Tax prove",
        "slug": "gas-land-there",
        "description": "Since point though fund say main decide despite. Personal one my. Involve care through suddenly.",
        "sku": "2606282615291",
        "price": 30.98,
        "discount_price": null,
        "currency": "USD",
        "stock": 264,
        "is_active": true,
        "rating": 4.7,
        "review_count": 336,
        "seller_id": "9503929f-e7c5-4ba4-9aec-61c1a6ad602f",
        "category_id": "1",
        "brand_id": "1"
    },
    {
        "id": "7a7fac59-9094-4ba4-ac28-b56d1097ecca",
        "title": "Science western back",
        "slug": "to-walk-over-guy",
        "description": "Find debate when tax activity purpose clear production. Western somebody story Democrat avoid.",
        "sku": "8484966568576",
        "price": 196.02,
        "discount_price": null,
        "currency": "USD",
        "stock": 121,
        "is_active": true,
        "rating": 1.1,
        "review_count": 320,
        "seller_id": "472acad9-7832-42a5-bd60-b83612a6e038",
        "category_id": "1",
        "brand_id": "1"
    },
    {
        "id": "58623f15-2d6e-4f60-998f-d1c8a3d6ef72",
        "title": "Senior fine raise",
        "slug": "control-moment",
        "description": "Success week example compare live. Federal word might. Could amount story pass unit central top.\nCatch garden allow style.\nArtist husband pull and go my least.",
        "sku": "9823607863820",
        "price": 387.46,
        "discount_price": 5.68,
        "currency": "USD",
        "stock": 224,
        "is_active": true,
        "rating": 2.3,
        "review_count": 466,
        "seller_id": "ad3ed306-dc0e-454a-9ec3-edcc3d5e56ea",
        "category_id": "1",
        "brand_id": "1"
    },
    {
        "id": "47925076-87fc-48e6-8b0a-e2ad7ee49d4b",
        "title": "Body lay",
        "slug": "return-result-allow",
        "description": "Fish reduce today notice policy. Perhaps she my dark cause discussion eight so.\nInterest improve business chair open sister get person. Even stay nature range. International your land seem add run.",
        "sku": "4566002842414",
        "price": 381.3,
        "discount_price": 290.44,
        "currency": "USD",
        "stock": 494,
        "is_active": true,
        "rating": 2.4,
        "review_count": 533,
        "seller_id": "9503929f-e7c5-4ba4-9aec-61c1a6ad602f",
        "category_id": "1",
        "brand_id": "1"
    },
    {
        "id": "91452c04-d4ee-4687-b327-ac8e49529626",
        "title": "Pressure dinner agency",
        "slug": "dark-indeed-economy",
        "description": "Find evidence tend begin out rich ago. Serious toward second style.\nDirector now use show chance yeah. Billion least son. Hit outside tree bring former compare.",
        "sku": "9617247839495",
        "price": 34.89,
        "discount_price": 283.78,
        "currency": "USD",
        "stock": 28,
        "is_active": true,
        "rating": 1.1,
        "review_count": 613,
        "seller_id": "489eb275-d47b-415b-829d-e9a2ed20f386",
        "category_id": "1",
        "brand_id": "1"
    },
    {
        "id": "e8b5546a-acf9-40af-b215-4aee43f47650",
        "title": "Now than yet exactly",
        "slug": "onto-fire-or-seven",
        "description": "Soon discover significant. Yeah develop herself heavy. No shoulder material avoid agree call south.",
        "sku": "5721456942458",
        "price": 50.13,
        "discount_price": 384.8,
        "currency": "USD",
        "stock": 216,
        "is_active": true,
        "rating": 3.7,
        "review_count": 698,
        "seller_id": "489eb275-d47b-415b-829d-e9a2ed20f386",
        "category_id": "1",
        "brand_id": "1"
    },
    {
        "id": "de135eb7-af5d-4a9c-b7bc-85425ebad120",
        "title": "Third",
        "slug": "speak-learn",
        "description": "Relate keep drop room. Significant that position throughout decade including. Modern if smile begin find.\nWould miss draw case among. Exactly herself better hear. Event firm where star.",
        "sku": "1037215523092",
        "price": 337.91,
        "discount_price": 271.89,
        "currency": "USD",
        "stock": 343,
        "is_active": true,
        "rating": 4.4,
        "review_count": 401,
        "seller_id": "ad3ed306-dc0e-454a-9ec3-edcc3d5e56ea",
        "category_id": "1",
        "brand_id": "1"
    },
    {
        "id": "82bddcce-853f-4e98-a871-105611a83363",
        "title": "Play usually couple",
        "slug": "resource-window",
        "description": "Maybe small responsibility relate worry. Admit foreign whatever call improve old.",
        "sku": "0247706947387",
        "price": 37.37,
        "discount_price": 151.87,
        "currency": "USD",
        "stock": 233,
        "is_active": true,
        "rating": 1.1,
        "review_count": 125,
        "seller_id": "da69d0ee-a499-4899-83dc-1831bf8eacbd",
        "category_id": "1",
        "brand_id": "1"
    },
    {
        "id": "7929cbe7-300e-42c6-84f5-713a0239b6a2",
        "title": "With effort",
        "slug": "money-conference",
        "description": "Financial here direction enter effort responsibility. Add understand direction kind.\nCommunity describe street compare budget. Read office here bar. Blood step fall field late.",
        "sku": "8409420506130",
        "price": 297.93,
        "discount_price": null,
        "currency": "USD",
        "stock": 4,
        "is_active": true,
        "rating": 2.3,
        "review_count": 583,
        "seller_id": "489eb275-d47b-415b-829d-e9a2ed20f386",
        "category_id": "1",
        "brand_id": "1"
    },
    {
        "id": "faa43873-fc63-4933-bc10-7950c3d8e766",
        "title": "While",
        "slug": "move-same-window",
        "description": "Many room head baby adult community understand season. Course yourself prove consumer.",
        "sku": "0053511763926",
        "price": 89.0,
        "discount_price": null,
        "currency": "USD",
        "stock": 120,
        "is_active": true,
        "rating": 3.8,
        "review_count": 847,
        "seller_id": "9503929f-e7c5-4ba4-9aec-61c1a6ad602f",
        "category_id": "1",
        "brand_id": "1"
    },
    {
        "id": "821c3367-2ac9-48f3-803d-6d5c0ce91d69",
        "title": "Themselves",
        "slug": "turn-letter-manager",
        "description": "Condition imagine natural fight good place before. Positive relate student great.\nWin mother manage. While along collection whose. Sort form case.",
        "sku": "8682007653025",
        "price": 433.61,
        "discount_price": 171.62,
        "currency": "USD",
        "stock": 331,
        "is_active": true,
        "rating": 5.0,
        "review_count": 79,
        "seller_id": "472acad9-7832-42a5-bd60-b83612a6e038",
        "category_id": "1",
        "brand_id": "1"
    },
    {
        "id": "34349ebb-6533-4f98-a229-9e4165de002b",
        "title": "Other soon attorney",
        "slug": "cause-time-a",
        "description": "Alone step many community up while room. Somebody road lay nice. Audience anyone coach catch pick not consumer.",
        "sku": "6881348234463",
        "price": 396.76,
        "discount_price": 137.26,
        "currency": "USD",
        "stock": 372,
        "is_active": true,
        "rating": 4.7,
        "review_count": 447,
        "seller_id": "489eb275-d47b-415b-829d-e9a2ed20f386",
        "category_id": "1",
        "brand_id": "1"
    },
    {
        "id": "235712a2-0572-476e-bc53-c22c21f831bd",
        "title": "Good activity",
        "slug": "common-on",
        "description": "Need reality nor social morning low eight. Result eye high animal.",
        "sku": "2723198768603",
        "price": 328.34,
        "discount_price": 183.87,
        "currency": "USD",
        "stock": 457,
        "is_active": true,
        "rating": 3.7,
        "review_count": 840,
        "seller_id": "ad3ed306-dc0e-454a-9ec3-edcc3d5e56ea",
        "category_id": "1",
        "brand_id": "1"
    },
    {
        "id": "3c67c891-ffb6-40a2-8e19-e8291ca02ea8",
        "title": "Pay guess",
        "slug": "evidence",
        "description": "Leave into guess him from how. Debate pay theory scene right consumer.\nFloor leave study respond difficult then. Actually interesting human door minute body.",
        "sku": "8349895677174",
        "price": 381.9,
        "discount_price": 144.33,
        "currency": "USD",
        "stock": 11,
        "is_active": true,
        "rating": 3.1,
        "review_count": 748,
        "seller_id": "472acad9-7832-42a5-bd60-b83612a6e038",
        "category_id": "1",
        "brand_id": "1"
    },
    {
        "id": "060ad911-230d-45b9-90c3-490a71ea7bb8",
        "title": "Tax for national",
        "slug": "fund-eye-start",
        "description": "Near we maintain adult. Boy major simply authority. Hard successful run serious. Word pretty from window government involve.",
        "sku": "0500344579540",
        "price": 243.87,
        "discount_price": 58.88,
        "currency": "USD",
        "stock": 281,
        "is_active": true,
        "rating": 1.8,
        "review_count": 332,
        "seller_id": "472acad9-7832-42a5-bd60-b83612a6e038",
        "category_id": "1",
        "brand_id": "1"
    },
    {
        "id": "0fae20e7-cbd3-4997-af5e-62635103e793",
        "title": "Investment mind easy",
        "slug": "inside-term-guy",
        "description": "Forward feel available firm receive. Develop up occur close arrive strong condition. Still half have difference.",
        "sku": "6132532402046",
        "price": 276.39,
        "discount_price": null,
        "currency": "USD",
        "stock": 345,
        "is_active": true,
        "rating": 1.9,
        "review_count": 676,
        "seller_id": "ad3ed306-dc0e-454a-9ec3-edcc3d5e56ea",
        "category_id": "1",
        "brand_id": "1"
    },
    {
        "id": "3f3552b2-186a-46ad-9317-80404a0dc51e",
        "title": "Whatever recognize not",
        "slug": "civil-nature",
        "description": "Explain you that ever whole operation man. Value various still meet form north. Camera third player challenge writer.\nAdmit find cup already citizen yes. Member like fill expert option address sit.",
        "sku": "5328411098634",
        "price": 391.38,
        "discount_price": null,
        "currency": "USD",
        "stock": 460,
        "is_active": true,
        "rating": 3.9,
        "review_count": 630,
        "seller_id": "9503929f-e7c5-4ba4-9aec-61c1a6ad602f",
        "category_id": "1",
        "brand_id": "1"
    },
    {
        "id": "7f1abf29-dbfd-48f1-a439-3390a7c583ad",
        "title": "Challenge improve",
        "slug": "thank-make-push",
        "description": "Low smile say group evidence artist evening. Our some me buy anyone community. Site guess fill west upon late ever. Difficult quite major think stand half.",
        "sku": "4269363576287",
        "price": 496.87,
        "discount_price": null,
        "currency": "USD",
        "stock": 148,
        "is_active": true,
        "rating": 4.8,
        "review_count": 644,
        "seller_id": "9503929f-e7c5-4ba4-9aec-61c1a6ad602f",
        "category_id": "1",
        "brand_id": "1"
    },
    {
        "id": "25bbe88f-0e27-497e-a8b3-55b1d4ec3ea7",
        "title": "Decide those camera camera",
        "slug": "help-east-radio-who",
        "description": "Lay into discover manage. Various debate situation pay per you stock.",
        "sku": "7785796970364",
        "price": 333.0,
        "discount_price": null,
        "currency": "USD",
        "stock": 428,
        "is_active": true,
        "rating": 5.0,
        "review_count": 424,
        "seller_id": "da69d0ee-a499-4899-83dc-1831bf8eacbd",
        "category_id": "1",
        "brand_id": "1"
    },
    {
        "id": "970a841c-9a6c-4bb5-8243-f2f7231926e3",
        "title": "Discussion surface",
        "slug": "order-job-plant",
        "description": "Across picture former PM child attorney. Group suffer wish father real conference.\nBlue quickly effect activity boy. Side lose check fear fly born. Like discussion know three American color.",
        "sku": "7391988405516",
        "price": 409.19,
        "discount_price": null,
        "currency": "USD",
        "stock": 10,
        "is_active": true,
        "rating": 3.3,
        "review_count": 843,
        "seller_id": "9503929f-e7c5-4ba4-9aec-61c1a6ad602f",
        "category_id": "1",
        "brand_id": "1"
    },
    {
        "id": "4985b73a-96d4-4ed7-8a69-0f58935467e4",
        "title": "Way wait",
        "slug": "economy-education",
        "description": "Everything finally cold case plant. However form sport language product action reach. Bit because miss else myself yourself accept.",
        "sku": "3680116039261",
        "price": 168.34,
        "discount_price": null,
        "currency": "USD",
        "stock": 378,
        "is_active": true,
        "rating": 1.8,
        "review_count": 152,
        "seller_id": "da69d0ee-a499-4899-83dc-1831bf8eacbd",
        "category_id": "1",
        "brand_id": "1"
    },
    {
        "id": "13e387ff-db99-402c-b7aa-cfc571915baf",
        "title": "Defense Republican",
        "slug": "matter-into-week",
        "description": "Particular already long parent agree on care. Ok whatever impact. Decide tend benefit debate.\nSuch involve record expect face. Wife present tax if house director.",
        "sku": "5256705863920",
        "price": 464.69,
        "discount_price": null,
        "currency": "USD",
        "stock": 112,
        "is_active": true,
        "rating": 3.6,
        "review_count": 669,
        "seller_id": "472acad9-7832-42a5-bd60-b83612a6e038",
        "category_id": "1",
        "brand_id": "1"
    }
]